idtrackerai/__init__.py
idtrackerai/blob.py
idtrackerai/fragment.py
idtrackerai/globalfragment.py
idtrackerai/list_of_blobs.py
idtrackerai/list_of_fragments.py
idtrackerai/list_of_global_fragments.py
idtrackerai/session.py
idtrackerai/GUI_tools/GUI_main_base.py
idtrackerai/GUI_tools/__init__.py
idtrackerai/GUI_tools/icon.svg
idtrackerai/GUI_tools/themes.py
idtrackerai/GUI_tools/tooltips.toml
idtrackerai/GUI_tools/widgets_utils/canvas.py
idtrackerai/GUI_tools/widgets_utils/custom_list.py
idtrackerai/GUI_tools/widgets_utils/id_labels.py
idtrackerai/GUI_tools/widgets_utils/other_utils.py
idtrackerai/GUI_tools/widgets_utils/sliders.py
idtrackerai/GUI_tools/widgets_utils/video_paths_holder.py
idtrackerai/GUI_tools/widgets_utils/video_player.py
idtrackerai/base/__init__.py
idtrackerai/base/run.py
idtrackerai/base/animals_detection/__init__.py
idtrackerai/base/animals_detection/animals_detection.py
idtrackerai/base/animals_detection/segmentation.py
idtrackerai/base/crossings_detection/__init__.py
idtrackerai/base/crossings_detection/crossing_detector.py
idtrackerai/base/crossings_detection/crossings_dataset.py
idtrackerai/base/crossings_detection/model_area.py
idtrackerai/base/fragmentation/__init__.py
idtrackerai/base/fragmentation/fragmentation.py
idtrackerai/base/network/__init__.py
idtrackerai/base/network/device.py
idtrackerai/base/network/models.py
idtrackerai/base/network/train.py
idtrackerai/base/postprocess/__init__.py
idtrackerai/base/postprocess/assign_them_all.py
idtrackerai/base/postprocess/correct_impossible_jumps.py
idtrackerai/base/postprocess/erosion.py
idtrackerai/base/postprocess/trajectories_creation.py
idtrackerai/base/tracker/__init__.py
idtrackerai/base/tracker/accumulation_manager.py
idtrackerai/base/tracker/accumulator.py
idtrackerai/base/tracker/assigner.py
idtrackerai/base/tracker/contrastive.py
idtrackerai/base/tracker/identity_transfer.py
idtrackerai/base/tracker/tracker.py
idtrackerai/data/test_A.avi
idtrackerai/data/test_B.avi
idtrackerai-6.0.13.dist-info/licenses/LICENSE
idtrackerai-6.0.13.dist-info/METADATA
idtrackerai-6.0.13.dist-info/WHEEL
idtrackerai-6.0.13.dist-info/entry_points.txt
idtrackerai-6.0.13.dist-info/top_level.txt
idtrackerai-6.0.13.dist-info/RECORD
