Metadata-Version: 2.4
Name: idtrackerai
Version: 6.0.13
Summary: idtracker.ai tracks up to 100 unmarked animals from videos recorded in laboratory conditions using artificial intelligence. Free and open source.
Author: Jordi Torrents, Francisco Romero Ferrero, Mattia G. Bergomi, Francisco J.H. Heras, Gonzalo Polavieja
Author-email: Main contact <info@idtracker.ai>
Project-URL: Homepage, https://idtracker.ai/
Project-URL: Repository, https://gitlab.com/polavieja_lab/idtrackerai
Project-URL: Issues, https://gitlab.com/polavieja_lab/idtrackerai/-/issues
Project-URL: Changelog, https://idtracker.ai/latest/user_guide/changelog.html
Classifier: Development Status :: 5 - Production/Stable
Classifier: Environment :: Console
Classifier: Intended Audience :: Science/Research
Classifier: Intended Audience :: Developers
Classifier: Environment :: X11 Applications :: Qt
Classifier: License :: OSI Approved :: GNU General Public License v3 or later (GPLv3+)
Classifier: Operating System :: OS Independent
Classifier: Programming Language :: Python
Classifier: Programming Language :: Python :: 3
Classifier: Programming Language :: Python :: 3.10
Classifier: Programming Language :: Python :: 3.11
Classifier: Programming Language :: Python :: 3.12
Classifier: Programming Language :: Python :: 3.13
Classifier: Topic :: Scientific/Engineering
Classifier: Topic :: Scientific/Engineering :: Artificial Intelligence
Requires-Python: >=3.10
License-File: LICENSE
Requires-Dist: numpy>=1.26.4
Requires-Dist: rich>=13.5.1
Requires-Dist: h5py>=3.10.0
Requires-Dist: scipy>=1.15.0
Requires-Dist: opencv-python-headless>=4.10.0.84
Requires-Dist: pyqt6>=6.7.0
Requires-Dist: qtpy>=2.4.0
Requires-Dist: superqt>=0.7.3
Requires-Dist: toml>=0.10.2
Requires-Dist: matplotlib>=3.7.0
Requires-Dist: packaging
Requires-Dist: psutil>=6.1.0
Requires-Dist: scikit-learn>=1.6.0
Requires-Dist: requests>=2.26.0
Requires-Dist: deprecated>=1.2.13
Provides-Extra: dev
Requires-Dist: pytest; extra == "dev"
Requires-Dist: black[jupyter]; extra == "dev"
Requires-Dist: pylint; extra == "dev"
Requires-Dist: vulture; extra == "dev"
Requires-Dist: isort; extra == "dev"
Requires-Dist: twine; extra == "dev"
Requires-Dist: build; extra == "dev"
Requires-Dist: pre-commit; extra == "dev"
Provides-Extra: docs
Requires-Dist: pydata_sphinx_theme; extra == "docs"
Requires-Dist: sphinx-copybutton; extra == "docs"
Requires-Dist: sphinx_design; extra == "docs"
Requires-Dist: sphinx>=5.0; extra == "docs"
Requires-Dist: nbsphinx; extra == "docs"
Requires-Dist: ipykernel; extra == "docs"
Requires-Dist: sphinx-toolbox; extra == "docs"
Requires-Dist: sphinx-togglebutton; extra == "docs"
Requires-Dist: esbonio; extra == "docs"
Requires-Dist: sphinx-favicon; extra == "docs"
Dynamic: license-file
